blcv/__init__.py
blcv/tools.py
blcv-0.1.0.dist-info/LICENSE
blcv-0.1.0.dist-info/METADATA
blcv-0.1.0.dist-info/WHEEL
blcv-0.1.0.dist-info/top_level.txt
blcv-0.1.0.dist-info/RECORD
