Metadata-Version: 2.1
Name: blcv
Version: 0.1.0
Summary: tools for using Blender for cv
Home-page: https://github.com/SarahWeiii/Blender_cv.git
Author: Xinyue Wei
Author-email: sarahwei0210@gmail.com
License: UNKNOWN
Platform: UNKNOWN
Classifier: Programming Language :: Python :: 3
Classifier: License :: OSI Approved :: MIT License
Classifier: Operating System :: OS Independent
Requires-Python: >=3.5
